crapdf-0.2.0.dist-info/METADATA
crapdf-0.2.0.dist-info/WHEEL
crapdf/crapdf.pyi
crapdf/__init__.py
crapdf/py.typed
crapdf/crapdf.pypy39-pp73-s390x-linux-gnu.so
crapdf-0.2.0.dist-info/RECORD
