Metadata-Version: 2.3
Name: crapdf
Version: 0.2.0
Classifier: Programming Language :: Rust
Classifier: Programming Language :: Python :: Implementation :: CPython
Classifier: Programming Language :: Python :: Implementation :: PyPy
Requires-Dist: pytest ; extra == 'tests'
Provides-Extra: tests
Summary: Extract text from a PDF file.
Requires-Python: >=3.8
Project-URL: Repository, https://github.com/AWeirdDev/crapdf
